hexonet.ispapicli-1.18.4-py3.7-nspkg.pth
hexonet/ispapicli/__init__.py
hexonet/ispapicli/ispapicli.py
hexonet/ispapicli/core/__init__.py
hexonet/ispapicli/core/core.py
hexonet/ispapicli/core/db.py
hexonet/ispapicli/core/scrap.py
hexonet/ispapicli/gui/__init__.py
hexonet/ispapicli/gui/login.py
hexonet/ispapicli/gui/mainframe.py
hexonet/ispapicli/icons/__init__.py
hexonet/ispapicli/icons/copy.png
hexonet/ispapicli/icons/cross.png
hexonet/ispapicli/icons/cut.png
hexonet/ispapicli/icons/direct-download.png
hexonet/ispapicli/icons/execute.png
hexonet/ispapicli/icons/help.png
hexonet/ispapicli/icons/login.png
hexonet/ispapicli/icons/logo-long.png
hexonet/ispapicli/icons/logo-x.png
hexonet/ispapicli/icons/logout.png
hexonet/ispapicli/icons/new.png
hexonet/ispapicli/icons/refresh.png
hexonet/ispapicli/icons/save.png
hexonet.ispapicli-1.18.4.dist-info/LICENSE
hexonet.ispapicli-1.18.4.dist-info/METADATA
hexonet.ispapicli-1.18.4.dist-info/WHEEL
hexonet.ispapicli-1.18.4.dist-info/dependency_links.txt
hexonet.ispapicli-1.18.4.dist-info/namespace_packages.txt
hexonet.ispapicli-1.18.4.dist-info/top_level.txt
hexonet.ispapicli-1.18.4.dist-info/zip-safe
hexonet.ispapicli-1.18.4.dist-info/RECORD
