Metadata-Version: 2.1
Name: hexonet.ispapicli
Version: 1.18.4
Summary: hexonet.ispapicli is a command line client library for the insanely fast HEXONET Backend API
Home-page: https://github.com/hexonet/ispapicli/
Author: Rashad Jamara
Author-email: rjamara@hexonet.net
Maintainer: Rashad Jamara
Maintainer-email: rjamara@hexonet.net
License: MIT
Classifier: Programming Language :: Python :: 3
Classifier: License :: OSI Approved :: MIT License
Classifier: Operating System :: OS Independent
Requires-Python: >=3.7
License-File: LICENSE
Requires-Dist: hexonet.apiconnector (<5,>=3)
Requires-Dist: PyQt5 (<6,>=5)
Requires-Dist: PyQt5-sip (<13,>=12)
Requires-Dist: tabulate (<1,>=0)
Requires-Dist: twine (<5,>=4)
Requires-Dist: tinydb (<5,>=4)
Requires-Dist: black
